coolname/__init__.py
coolname/__main__.py
coolname/config.py
coolname/exceptions.py
coolname/impl.py
coolname/loader.py
coolname/data/__init__.py
coolname/data/adjective.txt
coolname/data/adjective_first.txt
coolname/data/animal.txt
coolname/data/animal_breed.txt
coolname/data/animal_legendary.txt
coolname/data/color.txt
coolname/data/config.json
coolname/data/from2.txt
coolname/data/from_noun_no_mod.txt
coolname/data/noun_adjective.txt
coolname/data/of_modifier.txt
coolname/data/of_noun.txt
coolname/data/of_noun_no_mod.txt
coolname/data/prefix.txt
coolname/data/size.txt
coolname/data/subj2.txt
coolname-2.1.0.dist-info/LICENSE
coolname-2.1.0.dist-info/METADATA
coolname-2.1.0.dist-info/WHEEL
coolname-2.1.0.dist-info/entry_points.txt
coolname-2.1.0.dist-info/top_level.txt
coolname-2.1.0.dist-info/zip-safe
coolname-2.1.0.dist-info/RECORD
