Metadata-Version: 2.1
Name: coolname
Version: 2.1.0
Summary: Random name and slug generator
Home-page: https://github.com/alexanderlukanin13/coolname
Author: Alexander Lukanin
Author-email: alexander.lukanin.13@gmail.com
License: BSD
Keywords: coolname
Classifier: Development Status :: 5 - Production/Stable
Classifier: Intended Audience :: Developers
Classifier: License :: OSI Approved :: BSD License
Classifier: Natural Language :: English
Classifier: Programming Language :: Python :: 3
Classifier: Programming Language :: Python :: 3.6
Classifier: Programming Language :: Python :: 3.7
Classifier: Programming Language :: Python :: 3.8
Classifier: Programming Language :: Python :: 3.9
Classifier: Programming Language :: Python :: 3.10
License-File: LICENSE
